faccent/__init__.py
faccent/cam.py
faccent/clean_decorrelated.npy
faccent/mask.py
faccent/objectives.py
faccent/objectives_util.py
faccent/param.py
faccent/param_util.py
faccent/render.py
faccent/transform.py
faccent/utils.py
faccent/modelzoo/__init__.py
faccent/modelzoo/util.py
faccent/modelzoo/inceptionv1/InceptionV1.py
faccent/modelzoo/inceptionv1/__init__.py
faccent/modelzoo/inceptionv1/helper_layers.py
faccent-1.0.3.dist-info/METADATA
faccent-1.0.3.dist-info/WHEEL
faccent-1.0.3.dist-info/top_level.txt
faccent-1.0.3.dist-info/RECORD
