Metadata-Version: 2.1
Name: faccent
Version: 1.0.3
Summary: A pytorch tool for feature visualizations of various types
Home-page: https://github.com/chrishamblin7/faccent
Author: Chris Hamblin
Author-email: chrishamblin7@gmail.com
License: UNKNOWN
Platform: UNKNOWN
Classifier: Development Status :: 3 - Alpha
Classifier: License :: OSI Approved :: MIT License
Classifier: Programming Language :: Python :: 3
Classifier: Programming Language :: Python :: 3.7
Classifier: Programming Language :: Python :: 3.8
Classifier: Programming Language :: Python :: 3.9
Requires-Python: >=3.8
Requires-Dist: torch
Requires-Dist: torchvision
Requires-Dist: lucent ==0.1.0
Requires-Dist: kornia ==0.4.1
Requires-Dist: kaleido ==0.2.1
Requires-Dist: pyarrow >=14.0.1
Requires-Dist: nbformat >=5.7.3
Requires-Dist: einops >=0.6.1
Requires-Dist: ipywidgets >=8.0.7
Requires-Dist: scipy >=1.7.3
Requires-Dist: imageio
